Metadata-Version: 2.1
Name: django-eav2-updated-dependencies
Version: 1.3.1
Summary: Entity-Attribute-Value storage for Django
Home-page: https://github.com/jazzband/django-eav2
License: GNU Lesser General Public License (LGPL), Version 3
Keywords: django,django-eav2,database,eav,sql
Author: Mauro Lizaur
Author-email: mauro@sdf.org
Requires-Python: >=3.8,<4.0
Classifier: Development Status :: 3 - Alpha
Classifier: Environment :: Web Environment
Classifier: Framework :: Django
Classifier: Framework :: Django :: 3.2
Classifier: Framework :: Django :: 4.0
Classifier: Framework :: Django :: 4.1
Classifier: Intended Audience :: Developers
Classifier: License :: OSI Approved :: GNU Library or Lesser General Public License (LGPL)
Classifier: License :: Other/Proprietary License
Classifier: Programming Language :: Python
Classifier: Programming Language :: Python :: 3
Classifier: Programming Language :: Python :: 3.8
Classifier: Programming Language :: Python :: 3.9
Classifier: Programming Language :: Python :: 3.10
Classifier: Programming Language :: Python :: 3.11
Classifier: Topic :: Database
Classifier: Topic :: Software Development :: Libraries :: Python Modules
Provides-Extra: docs
Requires-Dist: django (>=3.2,<4.3)
Requires-Dist: m2r2 (>=0.3,<0.4) ; extra == "docs"
Requires-Dist: sphinx (>=5,<7) ; extra == "docs"
Requires-Dist: sphinx-autodoc-typehints (>=1.12,<2.0) ; extra == "docs"
Requires-Dist: sphinx-rtd-theme (>=1.0.0,<2.0.0) ; extra == "docs"
Requires-Dist: tomlkit (>=0.11,<0.12) ; extra == "docs"
Project-URL: Repository, https://github.com/jazzband/django-eav2
